tinkoff/__init__.py
tinkoff/base.py
tinkoff/py.typed
tinkoff/investments/__init__.py
tinkoff/investments/api/__init__.py
tinkoff/investments/api/base.py
tinkoff/investments/api/market.py
tinkoff/investments/api/operations.py
tinkoff/investments/api/orders.py
tinkoff/investments/api/portfolio.py
tinkoff/investments/api/sandbox.py
tinkoff/investments/api/user.py
tinkoff/investments/client/__init__.py
tinkoff/investments/client/environments.py
tinkoff/investments/client/exceptions.py
tinkoff/investments/client/rest.py
tinkoff/investments/client/streaming.py
tinkoff/investments/client/streaming.pyi
tinkoff/investments/model/__init__.py
tinkoff/investments/model/base.py
tinkoff/investments/model/operations.py
tinkoff/investments/model/orders.py
tinkoff/investments/model/portfolio.py
tinkoff/investments/model/response.py
tinkoff/investments/model/sandbox.py
tinkoff/investments/model/streaming.py
tinkoff/investments/model/market/__init__.py
tinkoff/investments/model/market/candles.py
tinkoff/investments/model/market/instruments.py
tinkoff/investments/model/market/orderbook.py
tinkoff/investments/model/user/__init__.py
tinkoff/investments/model/user/accounts.py
tinkoff/investments/utils/__init__.py
tinkoff/investments/utils/historical_data.py
tinkoff_api-1.19.dist-info/LICENSE
tinkoff_api-1.19.dist-info/METADATA
tinkoff_api-1.19.dist-info/WHEEL
tinkoff_api-1.19.dist-info/top_level.txt
tinkoff_api-1.19.dist-info/RECORD
