Metadata-Version: 2.1
Name: tinkoff-api
Version: 1.19
Summary: Python Tinkoff API client for asyncio and humans
Home-page: https://github.com/Fatal1ty/tinkoff-api
Author: Alexander Tikhonov
Author-email: random.gauss@gmail.com
License: Apache License, Version 2.0
Platform: all
Classifier: License :: OSI Approved :: Apache Software License
Classifier: Intended Audience :: Developers
Classifier: Topic :: Office/Business :: Financial
Classifier: Topic :: Office/Business :: Financial :: Investment
Classifier: Programming Language :: Python :: 3 :: Only
Classifier: Programming Language :: Python :: 3.6
Classifier: Programming Language :: Python :: 3.7
Classifier: Programming Language :: Python :: 3.8
Classifier: Development Status :: 4 - Beta
Requires-Python: >=3.6
License-File: LICENSE
Requires-Dist: aiohttp (<4,>=3.6.2)
Requires-Dist: yarl (>=1.4.2)
Requires-Dist: mashumaro (<4,>=3.0)
Requires-Dist: ciso8601 (==2.1.2)
